gradgpad/VERSION
gradgpad/__init__.py
gradgpad/public_api.py
gradgpad/cli/__init__.py
gradgpad/cli/command_line.py
gradgpad/data/gradgpad_annotations.json
gradgpad/data/lifelong_learning/devel_pai_tasks.json
gradgpad/data/lifelong_learning/test_pai_tasks.json
gradgpad/data/lifelong_learning/train_pai_tasks.json
gradgpad/data/protocols/protocol_Grandtest_Train_Type_PAI_I_Test_All.json
gradgpad/data/protocols/protocol_cross_dataset_casia_fasd.json
gradgpad/data/protocols/protocol_cross_dataset_csmad.json
gradgpad/data/protocols/protocol_cross_dataset_hkbu.json
gradgpad/data/protocols/protocol_cross_dataset_hkbuV2.json
gradgpad/data/protocols/protocol_cross_dataset_msu_mfsd.json
gradgpad/data/protocols/protocol_cross_dataset_oulu_npu.json
gradgpad/data/protocols/protocol_cross_dataset_replay_attack.json
gradgpad/data/protocols/protocol_cross_dataset_replay_mobile.json
gradgpad/data/protocols/protocol_cross_dataset_rose_youtu.json
gradgpad/data/protocols/protocol_cross_dataset_siw.json
gradgpad/data/protocols/protocol_cross_dataset_siw_m.json
gradgpad/data/protocols/protocol_cross_dataset_threedmad.json
gradgpad/data/protocols/protocol_cross_dataset_uvad.json
gradgpad/data/protocols/protocol_cross_device_digital_camera.json
gradgpad/data/protocols/protocol_cross_device_mobile_tablet.json
gradgpad/data/protocols/protocol_cross_device_webcam.json
gradgpad/data/protocols/protocol_lodo_casia_fasd.json
gradgpad/data/protocols/protocol_lodo_csmad.json
gradgpad/data/protocols/protocol_lodo_hkbu.json
gradgpad/data/protocols/protocol_lodo_hkbuV2.json
gradgpad/data/protocols/protocol_lodo_msu_mfsd.json
gradgpad/data/protocols/protocol_lodo_oulu_npu.json
gradgpad/data/protocols/protocol_lodo_replay_attack.json
gradgpad/data/protocols/protocol_lodo_replay_mobile.json
gradgpad/data/protocols/protocol_lodo_rose_youtu.json
gradgpad/data/protocols/protocol_lodo_siw.json
gradgpad/data/protocols/protocol_lodo_siw_m.json
gradgpad/data/protocols/protocol_lodo_threedmad.json
gradgpad-2.1.0.dist-info/LICENSE
gradgpad-2.1.0.dist-info/METADATA
gradgpad-2.1.0.dist-info/WHEEL
gradgpad-2.1.0.dist-info/entry_points.txt
gradgpad-2.1.0.dist-info/top_level.txt
gradgpad-2.1.0.dist-info/RECORD
