Metadata-Version: 2.1
Name: gradgpad
Version: 2.1.0
Summary: gradgpad
Home-page: https://github.com/acostapazo/gradgpad
Author: ALiCE Biometrics
Author-email: acosta@alicebiometrics.com
License: MIT
Keywords: face-PAD,framework,evaluation
Platform: UNKNOWN
Classifier: License :: OSI Approved :: MIT License
Classifier: Programming Language :: Python
Classifier: Programming Language :: Python :: 3
Classifier: Programming Language :: Python :: 3 :: Only
Classifier: Programming Language :: Python :: 3.6
Classifier: Programming Language :: Python :: 3.7
Classifier: Programming Language :: Python :: 3.8
Classifier: Programming Language :: Python :: 3.9
Classifier: Programming Language :: Python :: 3.10
Classifier: Programming Language :: Python :: 3.11
License-File: LICENSE
Requires-Dist: pyte
Requires-Dist: pandas (<2)
Requires-Dist: seaborn (<1)
Requires-Dist: tabulate (<1)
Requires-Dist: scikit-learn (<1) ; python_version < "3.7"
Requires-Dist: scikit-learn (<2) ; python_version >= "3.7"
